gcp_secretmanager_cache/__init__.py
gcp_secretmanager_cache/_version.py
gcp_secretmanager_cache/cache_secret.py
gcp_secretmanager_cache/decorators.py
gcp_secretmanager_cache/exceptions.py
gcp_secretmanager_cache/managers.py
gcp_secretmanager_cache/tests/__init__.py
gcp_secretmanager_cache/tests/test_gcp_secretmanager_cache.py
gcp_secretmanager_cache-0.4.8.dist-info/licenses/LICENSE
gcp_secretmanager_cache-0.4.8.dist-info/METADATA
gcp_secretmanager_cache-0.4.8.dist-info/WHEEL
gcp_secretmanager_cache-0.4.8.dist-info/top_level.txt
gcp_secretmanager_cache-0.4.8.dist-info/RECORD
