Metadata-Version: 2.4
Name: gcp_secretmanager_cache
Version: 0.4.8
Summary: A utility to cache google cloud platform secrets and allow concurrent access that also always provides the latest enabled version of a secret
Home-page: https://github.com/Mikemoore63/gcp-secretmanager-cache
Author: Mike Moore
Author-email: z_z_zebra@yahoo.com
License: MIT
Classifier: Programming Language :: Python :: 3
Classifier: Operating System :: OS Independent
License-File: LICENSE
Requires-Dist: google-cloud-secret-manager~=2.0
Requires-Dist: google-api-python-client<3.0,>1.0
Requires-Dist: google-cloud-storage<4.0,>1.0
Requires-Dist: grpcio~=1.0
Requires-Dist: python-dateutil~=2.0
Requires-Dist: pytz>=2022.0
Dynamic: author
Dynamic: author-email
Dynamic: classifier
Dynamic: description
Dynamic: description-content-type
Dynamic: home-page
Dynamic: license
Dynamic: license-file
Dynamic: requires-dist
Dynamic: summary
